ZeroEx/ZeroEx.py
ZeroEx/__init__.py
ZeroEx/test_0x.py
0x_python-1.0.16.dist-info/METADATA
0x_python-1.0.16.dist-info/WHEEL
0x_python-1.0.16.dist-info/entry_points.txt
0x_python-1.0.16.dist-info/top_level.txt
0x_python-1.0.16.dist-info/RECORD
