Metadata-Version: 2.1
Name: 0x-python
Version: 1.0.16
Summary: 0x python wrapper
Home-page: https://github.com/skeetzo/0x-python
Author: Skeetzo
Author-email: WebmasterSkeetzo@gmail.com
License: UNKNOWN
Keywords: 0x,api,python
Platform: UNKNOWN
Classifier: Development Status :: 5 - Production/Stable
Classifier: Environment :: Console
Classifier: Intended Audience :: Developers
Classifier: Topic :: Office/Business :: Financial :: Investment
Classifier: License :: OSI Approved :: MIT License
Classifier: Natural Language :: English
Classifier: Operating System :: POSIX :: Linux
Classifier: Programming Language :: Python :: 3
Classifier: Topic :: Software Development :: Libraries :: Python Modules
Requires-Dist: requests
